CHANGES.txt
MANIFEST.in
README.md
setup.py
PGeoTRMM.egg-info/PKG-INFO
PGeoTRMM.egg-info/SOURCES.txt
PGeoTRMM.egg-info/dependency_links.txt
PGeoTRMM.egg-info/top_level.txt
pgeotrmm/.gitignore
pgeotrmm/__init__.py
pgeotrmm/__init__.pyc
pgeotrmm/config/__init__.py
pgeotrmm/config/__init__.pyc
pgeotrmm/config/trmm.json
pgeotrmm/core/.gitignore
pgeotrmm/core/__init__.py
pgeotrmm/core/__init__.pyc
pgeotrmm/core/trmm_core.py
pgeotrmm/core/trmm_core.pyc
pgeotrmm/rest/__init__.py
pgeotrmm/rest/__init__.pyc
pgeotrmm/rest/trmm_rest.py
pgeotrmm/rest/trmm_rest.pyc