Metadata-Version: 1.0
Name: PGeoTRMM
Version: 0.1.1
Summary: TRMM plug-in for PGeo.
Home-page: http://pypi.python.org/pypi/PGeoTRMM/
Author: Simone Murzilli; Guido Barbaglia
Author-email: geobrickspy@gmail.com
License: LICENSE.txt
Platform: UNKNOWN
